G1Race.py
G1Race-0.0.7.dist-info/METADATA
G1Race-0.0.7.dist-info/WHEEL
G1Race-0.0.7.dist-info/entry_points.txt
G1Race-0.0.7.dist-info/top_level.txt
G1Race-0.0.7.dist-info/RECORD
